{
  "main": {
    "id": "547e55ea84485208",
    "type": "split",
    "children": [
      {
        "id": "e74e857ac52d5bb8",
        "type": "tabs",
        "children": [
          {
            "id": "9ce0f88790dacf58",
            "type": "leaf",
            "state": {
              "type": "markdown",
              "state": {
                "file": "23_Attacking Common Applications/23_Attacking Common Applications.md",
                "mode": "source",
                "source": false
              },
              "icon": "lucide-file",
              "title": "23_Attacking Common Applications"
            }
          }
        ]
      }
    ],
    "direction": "vertical"
  },
  "left": {
    "id": "101743bf707d586e",
    "type": "split",
    "children": [
      {
        "id": "40ee4fbf9c716904",
        "type": "tabs",
        "children": [
          {
            "id": "3a3b560d8f32d9fd",
            "type": "leaf",
            "state": {
              "type": "search",
              "state": {
                "query": "",
                "matchingCase": false,
                "explainSearch": false,
                "collapseAll": false,
                "extraContext": false,
                "sortOrder": "alphabetical"
              },
              "icon": "lucide-search",
              "title": "Search"
            }
          },
          {
            "id": "3a58a60268c11b8e",
            "type": "leaf",
            "state": {
              "type": "bookmarks",
              "state": {},
              "icon": "lucide-bookmark",
              "title": "Bookmarks"
            }
          },
          {
            "id": "66a2b44cf73aca22",
            "type": "leaf",
            "state": {
              "type": "file-explorer",
              "state": {
                "sortOrder": "alphabetical",
                "autoReveal": false
              },
              "icon": "lucide-folder-closed",
              "title": "Files"
            }
          }
        ],
        "currentTab": 2
      }
    ],
    "direction": "horizontal",
    "width": 300
  },
  "right": {
    "id": "ba07d858ae33f008",
    "type": "split",
    "children": [
      {
        "id": "56090b73e1f83f8e",
        "type": "tabs",
        "children": [
          {
            "id": "b473639657be0a67",
            "type": "leaf",
            "state": {
              "type": "backlink",
              "state": {
                "file": "19_File Inclusion/19_File Inclusion.md",
                "collapseAll": true,
                "extraContext": false,
                "sortOrder": "alphabetical",
                "showSearch": false,
                "searchQuery": "",
                "backlinkCollapsed": false,
                "unlinkedCollapsed": true
              },
              "icon": "links-coming-in",
              "title": "Backlinks for 19_File Inclusion"
            }
          },
          {
            "id": "b42c18e9baef82bb",
            "type": "leaf",
            "state": {
              "type": "outgoing-link",
              "state": {
                "file": "HackTheBox Heal.md",
                "linksCollapsed": false,
                "unlinkedCollapsed": true
              },
              "icon": "links-going-out",
              "title": "Outgoing links from HackTheBox Heal"
            }
          },
          {
            "id": "f4ca6912c13ff787",
            "type": "leaf",
            "state": {
              "type": "tag",
              "state": {
                "sortOrder": "alphabetical",
                "useHierarchy": false,
                "showSearch": false,
                "searchQuery": ""
              },
              "icon": "lucide-tags",
              "title": "Tags"
            }
          },
          {
            "id": "683a2dfd49bb901a",
            "type": "leaf",
            "state": {
              "type": "outline",
              "state": {
                "file": "23_Attacking Common Applications/23_Attacking Common Applications.md",
                "followCursor": true,
                "showSearch": true,
                "searchQuery": ""
              },
              "icon": "lucide-list",
              "title": "Outline of 23_Attacking Common Applications"
            }
          }
        ],
        "currentTab": 3
      }
    ],
    "direction": "horizontal",
    "width": 288.5
  },
  "left-ribbon": {
    "hiddenItems": {
      "switcher:Open quick switcher": false,
      "graph:Open graph view": false,
      "canvas:Create new canvas": false,
      "daily-notes:Open today's daily note": false,
      "templates:Insert template": false,
      "command-palette:Open command palette": false
    }
  },
  "active": "9ce0f88790dacf58",
  "lastOpenFiles": [
    "23_Attacking Common Applications/images/118.png",
    "23_Attacking Common Applications/images/105.png",
    "23_Attacking Common Applications/23_Attacking Common Applications.md",
    "23_Attacking Common Applications/images/127.png",
    "23_Attacking Common Applications/images/126.png",
    "23_Attacking Common Applications/images/125.png",
    "23_Attacking Common Applications/images/124.png",
    "23_Attacking Common Applications/images/123.png",
    "23_Attacking Common Applications/images/122.png",
    "23_Attacking Common Applications/images/121.png",
    "23_Attacking Common Applications/images/120.png",
    "23_Attacking Common Applications/images/119.png",
    "13_Using Web Proxies/13_Using Web Proxies.md",
    "23_Attacking Common Applications/Attacking_Common_Applications_Module_Cheat_Sheet.pdf",
    "23_Attacking Common Applications/images",
    "22_Web Attacks/22_Web Attacks.md",
    "23_Attacking Common Applications",
    "22_Web Attacks/Web_Attacks_Module_Cheat_Sheet.pdf",
    "22_Web Attacks/images",
    "22_Web Attacks",
    "21_Command_Injections/21_Command_Injections.md",
    "21_Command_Injections/Command_Injections_Module_Cheat_Sheet.pdf",
    "20_File Upload Attacks/20_File Upload Attacks.md",
    "21_Command_Injections/images",
    "21_Command_Injections",
    "20_File Upload Attacks/File_Upload_Attacks_Module_Cheat_Sheet.pdf",
    "19_File Inclusion/19_File Inclusion.md",
    "18_Cross-Site Scripting (XSS)/18_Cross-Site Scripting (XSS).md",
    "9_Password Attacks/9_Password Attacks.md",
    "17_SQLMap Essentials/17_SQLMap Essentials.md",
    "Untitled 1.md",
    "4_Footprinting/4. Footprinting.md",
    "16_SQL Injection Fundamentals/16_SQL Injection Fundamentals.md",
    "15_Login Brute Forcing/15_Login Brute Forcing.md",
    "14_Attacking Web Applications with Ffuf/14_Attacking Web Applications with Ffuf.md",
    "12_Active Directory Enumeration & Attacks/Tools-of-the-trade/Tools-of-the-Trade.md",
    "12_Active Directory Enumeration & Attacks/12_Active Directory Enumeration & Attacks.md",
    "11_Pivoting, Tunneling, and Port Forwarding/11_Pivoting, Tunneling, and Port Forwarding.md",
    "12_Active Directory Enumeration & Attacks/Tools-of-the-trade/Tools of the trade.md",
    "10_Attacking Common Services/10_Attacking Common Services.md",
    "8_Using the Metasploit Framework/8_Using the Metasploit Framework.md",
    "7_Shells & Payloads/7_Shells & Payloads.md",
    "6_File Transfers/6_File Transfers.md",
    "7_Shells & Payloads.md",
    "5_Information Gathering - Web Edition/5_Information Gathering - Web Edition.md",
    "5_Information Gathering - Web Edition/5. Information Gathering - Web Edition.md"
  ]
}